suma_ulsa-0.2.6.dist-info/METADATA
suma_ulsa-0.2.6.dist-info/WHEEL
suma_ulsa/__init__.py
suma_ulsa/_internal/__init__.py
suma_ulsa/boolean_algebra/__init__.py
suma_ulsa/boolean_algebra/boolean_algebra.py
suma_ulsa/boolean_algebra/boolean_algebra.pyi
suma_ulsa/conversions/__init__.py
suma_ulsa/conversions/conversions.py
suma_ulsa/conversions/conversions.pyi
suma_ulsa/networking/__init__.py
suma_ulsa/networking/networking.py
suma_ulsa/networking/networking.pyi
suma_ulsa/py.typed
suma_ulsa/suma_ulsa_native.cp313-win_amd64.pyd
suma_ulsa-0.2.6.dist-info/RECORD
