Metadata-Version: 2.4
Name: suma_ulsa
Version: 0.2.6
Summary: Sistema Universitario de Métodos Académicos (SUMA) - librería Python con backend en Rust
Author-email: Ari Castillo <castilloari282@gmail.com>
License: MIT
Requires-Python: >=3.10
